MANIFEST.in
requirements.txt
setup.py
kvmd/__init__.py
kvmd/__main__.py
kvmd/application.py
kvmd/atx.py
kvmd/gpio.py
kvmd/logging.py
kvmd/msd.py
kvmd/ps2.py
kvmd/server.py
kvmd/streamer.py
kvmd.egg-info/PKG-INFO
kvmd.egg-info/SOURCES.txt
kvmd.egg-info/dependency_links.txt
kvmd.egg-info/entry_points.txt
kvmd.egg-info/requires.txt
kvmd.egg-info/top_level.txt
kvmd/extras/__init__.py
kvmd/extras/cleanup/__init__.py
kvmd/extras/cleanup/__main__.py
kvmd/extras/wscli/__init__.py
kvmd/extras/wscli/__main__.py