Metadata-Version: 1.1
Name: kvmd
Version: 0.10
Summary: The main Pi-KVM daemon
Home-page: https://github.com/mdevaev/pi-kvm
Author: Maxim Devaev
Author-email: mdevaev@gmail.com
License: GPLv3
Platform: any
Classifier: License :: OSI Approved :: GNU General Public License v3 or later (GPLv3+)
Classifier: Development Status :: 3 - Alpha
Classifier: Programming Language :: Python :: 3.6
Classifier: Topic :: System :: Systems Administration
Classifier: Operating System :: POSIX :: Linux
Classifier: Intended Audience :: System Administrators
Classifier: Intended Audience :: End Users/Desktop
Classifier: Intended Audience :: Telecommunications Industry
